{
  "background_message_service_not_initialized": {
    "message": "MessageService 尚未初始化",
    "description": "消息服务未初始化错误"
  },
  "background_init_failed": {
    "message": "导航图谱后台初始化失败",
    "description": "后台初始化失败错误"
  },
  "background_session_manager_init_start": {
    "message": "初始化会话管理器...",
    "description": "会话管理器初始化开始日志"
  },
  "background_nav_manager_init_start": {
    "message": "初始化导航管理器...",
    "description": "导航管理器初始化开始日志"
  },
  "background_register_base_handlers_start": {
    "message": "注册基础消息处理程序...",
    "description": "基础消息处理程序注册开始日志"
  },
  "background_settings_service_init_start": {
    "message": "初始化设置服务...",
    "description": "设置服务初始化开始日志"
  },
  "background_message_service_init_start": {
    "message": "初始化消息服务...",
    "description": "消息服务初始化开始日志"
  },
  "background_register_session_handlers_start": {
    "message": "注册会话管理器消息处理程序...",
    "description": "会话管理器消息处理程序注册开始日志"
  },
  "background_init_complete": {
    "message": "导航图谱后台初始化成功",
    "description": "后台初始化成功日志"
  },
  "background_startup_begin": {
    "message": "Navigraph 后台脚本启动",
    "description": "后台脚本启动消息"
  },
  "background_init_start": {
    "message": "初始化后台服务...",
    "description": "后台服务初始化开始"
  }
}
